<?xml version="1.1" encoding="UTF-8" standalone="no"?>
<databaseChangeLog xmlns="http://www.liquibase.org/xml/ns/dbchangelog" xmlns:ext="http://www.liquibase.org/xml/ns/dbchangelog-ext" xmlns:xsi="http://www.w3.org/2001/XMLSchema-instance" xsi:schemaLocation="http://www.liquibase.org/xml/ns/dbchangelog-ext http://www.liquibase.org/xml/ns/dbchangelog/dbchangelog-ext.xsd http://www.liquibase.org/xml/ns/dbchangelog http://www.liquibase.org/xml/ns/dbchangelog/dbchangelog-3.6.xsd">
    <changeSet author="j.hoermann" id="d1440b93-e01c-406b-9f0d-c55cac877fcd">                  
        <insert tableName="AB_KEYWORD_ENTRY">
            <column name="AB_KEYWORD_ENTRYID" value="2ef84e0e-988a-44b4-9d14-3461555d2f18"/>
            <column name="KEYID" value="TICKET"/>
            <column name="TITLE" value="Ticket"/>
            <column name="CONTAINER" value="TaskType"/>
            <column name="SORTING" valueNumeric="1"/>
            <column name="ISACTIVE" valueNumeric="1"/>
            <column name="ISESSENTIAL" valueNumeric="1"/>
        </insert>
    </changeSet>
</databaseChangeLog>