<?xml version="1.1" encoding="UTF-8" standalone="no"?>
<databaseChangeLog xmlns="http://www.liquibase.org/xml/ns/dbchangelog" xmlns:ext="http://www.liquibase.org/xml/ns/dbchangelog-ext" xmlns:xsi="http://www.w3.org/2001/XMLSchema-instance" xsi:schemaLocation="http://www.liquibase.org/xml/ns/dbchangelog-ext http://www.liquibase.org/xml/ns/dbchangelog/dbchangelog-ext.xsd http://www.liquibase.org/xml/ns/dbchangelog http://www.liquibase.org/xml/ns/dbchangelog/dbchangelog-3.6.xsd">
    <changeSet author="a.veogl" id="3e9548bd-2c3e-413f-a8b0-405d926f2790">
        <update tableName="AB_KEYWORD_ENTRY">
            <column name="TITLE" value="Price policy"/>
            <where>AB_KEYWORD_ENTRYID = ? and TITLE = ?</where>
            <whereParams>
                <param value="7963d4ed-f7a7-4a9f-aa86-fea42167145f"/>
                <param value="Strength 1"/>
            </whereParams>
        </update>
        
        <update tableName="AB_KEYWORD_ENTRY">
            <column name="TITLE" value="Personal appearance"/>
            <where>AB_KEYWORD_ENTRYID = ? and TITLE = ?</where>
            <whereParams>
                <param value="2cacfe09-7dcd-454a-b263-46aee796bc21"/>
                <param value="Strength 2"/>
            </whereParams>
        </update>
        
        <update tableName="AB_KEYWORD_ENTRY">
            <column name="TITLE" value="Product content"/>
            <where>AB_KEYWORD_ENTRYID = ? and TITLE = ?</where>
            <whereParams>
                <param value="919cffee-5943-4105-a5bc-a14bd33b9f67"/>
                <param value="Strength 3"/>
            </whereParams>
        </update>
        
        
        <update tableName="AB_KEYWORD_ENTRY">
            <column name="TITLE" value="Know How"/>
            <where>AB_KEYWORD_ENTRYID = ? and TITLE = ?</where>
            <whereParams>
                <param value="fd012937-8fe7-418e-8e55-80b3b5db331c"/>
                <param value="Weakness 1"/>
            </whereParams>
        </update>
        
        <update tableName="AB_KEYWORD_ENTRY">
            <column name="TITLE" value="Market situation"/>
            <where>AB_KEYWORD_ENTRYID = ? and TITLE = ?</where>
            <whereParams>
                <param value="b62e1a05-af41-4d2d-978c-6c2950b202d8"/>
                <param value="Weakness 2"/>
            </whereParams>
        </update>
        
        <update tableName="AB_KEYWORD_ENTRY">
            <column name="TITLE" value="Liquidity"/>
            <where>AB_KEYWORD_ENTRYID = ? and TITLE = ?</where>
            <whereParams>
                <param value="294db00d-6237-4db8-b7b6-41c5dc79a1e4"/>
                <param value="Weakness 3"/>
            </whereParams>
        </update>
    </changeSet>
</databaseChangeLog>