<?xml version="1.1" encoding="UTF-8" standalone="no"?>
<databaseChangeLog xmlns="http://www.liquibase.org/xml/ns/dbchangelog" xmlns:ext="http://www.liquibase.org/xml/ns/dbchangelog-ext" xmlns:xsi="http://www.w3.org/2001/XMLSchema-instance" xsi:schemaLocation="http://www.liquibase.org/xml/ns/dbchangelog-ext http://www.liquibase.org/xml/ns/dbchangelog/dbchangelog-ext.xsd http://www.liquibase.org/xml/ns/dbchangelog http://www.liquibase.org/xml/ns/dbchangelog/dbchangelog-3.6.xsd">
    <changeSet author="j.hoermann" id="20746857-768f-420b-b3d6-61fa207452fd">
      <preConditions onFail="MARK_RAN">
        <not>
          <tableExists tableName="SALESPROJECT_CYCLE"/>
        </not>
      </preConditions>
        <createTable tableName="SALESPROJECT_CYCLE">
            <column name="SALESPROJECT_CYCLEID" type="CHAR(36)">
                <constraints primaryKey="true"/>
            </column>
            <column name="SALESPROJECT_ID" type="CHAR(36)">
                <constraints nullable="false"/>
            </column>
            
            <column name="KIND" type="INTEGER"/>
            <column name="MILESTONEVALUE" type="INTEGER"/>
            
            <column name="DATE_START" type="DATETIME"/>
            <column name="DATE_END" type="DATETIME"/>
        </createTable>
    </changeSet>
</databaseChangeLog>