<?xml version="1.1" encoding="UTF-8" standalone="no"?>
<databaseChangeLog xmlns="http://www.liquibase.org/xml/ns/dbchangelog"
    xmlns:xsi="http://www.w3.org/2001/XMLSchema-instance"
    xsi:schemaLocation="http://www.liquibase.org/xml/ns/dbchangelog http://www.liquibase.org/xml/ns/dbchangelog/dbchangelog-3.6.xsd">
  <changeSet author="v.broens" id="bf635bf3-a1db-4c23-8a09-718b98847aa4">
        <insert tableName="AB_KEYWORD_ENTRY">
            <column name="AB_KEYWORD_ENTRYID" value="26c175af-c13d-4056-8ac3-b69a3dcb387c"/>
            <column name="KEYID" value="CONTACTSERVICE"/>
            <column name="TITLE" value="Service"/>
            <column name="CONTAINER" value="ContactDepartment"/>
            <column name="SORTING" valueNumeric="5"/>
            <column name="ISACTIVE" valueNumeric="1"/>
            <column name="ISESSENTIAL" valueNumeric="0"/>
            <column  name="AB_KEYWORD_CATEGORY_ID"  value="cda5deac-5b7c-4c98-9904-2eb3b224235d"/>
        </insert>
  </changeSet>
</databaseChangeLog>