<databaseChangeLog xmlns="http://www.liquibase.org/xml/ns/dbchangelog" xmlns:ext="http://www.liquibase.org/xml/ns/dbchangelog-ext" xmlns:xsi="http://www.w3.org/2001/XMLSchema-instance" xsi:schemaLocation="http://www.liquibase.org/xml/ns/dbchangelog-ext http://www.liquibase.org/xml/ns/dbchangelog/dbchangelog-ext.xsd http://www.liquibase.org/xml/ns/dbchangelog http://www.liquibase.org/xml/ns/dbchangelog/dbchangelog-3.6.xsd">
  <changeSet author="autogenerated" id="99cb8d21-38ab-4c4c-a667-71662d1716f1">
    <update tableName="AB_KEYWORD_ATTRIBUTE">
      <column name="AB_KEYWORD_CATEGORY_ID" value="e23c8316-d43a-4606-803e-d4488823cc52"/>
      <where>AB_KEYWORD_ATTRIBUTEID = '37973717-5565-4035-848a-0d682990d301'</where>
    </update>
    <update tableName="AB_KEYWORD_ATTRIBUTE">
      <column name="AB_KEYWORD_CATEGORY_ID" value="e23c8316-d43a-4606-803e-d4488823cc52"/>
      <where>AB_KEYWORD_ATTRIBUTEID = 'c31e0ba9-4c95-495e-ad90-0e1a1a92e834'</where>
    </update>
  </changeSet>
</databaseChangeLog>

