<?xml version="1.1" encoding="UTF-8" standalone="no"?>
<databaseChangeLog xmlns="http://www.liquibase.org/xml/ns/dbchangelog" xmlns:ext="http://www.liquibase.org/xml/ns/dbchangelog-ext" xmlns:xsi="http://www.w3.org/2001/XMLSchema-instance" xsi:schemaLocation="http://www.liquibase.org/xml/ns/dbchangelog-ext http://www.liquibase.org/xml/ns/dbchangelog/dbchangelog-ext.xsd http://www.liquibase.org/xml/ns/dbchangelog http://www.liquibase.org/xml/ns/dbchangelog/dbchangelog-3.6.xsd">
  <changeSet author="autogenerated" id="a21e638d-4a5e-4b1b-b86e-2393067689d6">
    <delete tableName="BULKMAIL"/>
    <insert tableName="BULKMAIL">
      <column name="SENDER_EMAIL_ADDRESS" value="meinefirma@adito.de"/>
      <column name="BULKMAILID" value="0e7d1178-548a-4ea7-a7ec-0447fe594624"/>
      <column name="SUBJECT" value="Follow up: Kundentag bei meineFirma"/>
      <column name="PLACEOFUSE" value="Event"/>
      <column name="DESCRIPTION" value="(Mosaico-) Follow up - no shows zum Internen Kundentag. Eingeladen werden Geschäftsführer sowie andere Leitungs Positionen. "/>
      <column name="MOSAICOTEMPLATE_ID" value="fb9706a8-4394-4fb4-8fc4-c83416b3d1ed"/>
      <column name="USER_EDIT" value="Admin"/>
      <column name="SENDTYPE" value="SENDTYPE_MANUAL"/>
      <column name="USER_NEW" value="Lisa Sommer"/>
      <column name="INTEREST_ID" value="2ad0e569-b9eb-4261-9cc7-4ed59e43a7ac"/>
      <column name="EMPLOYEE_CONTACT_ID" value="ef345d11-a40d-59e0-a24c-afcb6095d2cb"/>
      <column name="DATE_NEW" valueDate="2023-06-02T13:12:13"/>
      <column name="CREATEACTIVITIES" valueNumeric="0"/>
      <column name="ISOLANGUAGE" value="deu"/>
      <column name="NAME" value="meineFirma Kundentag (5): Follow up - no show"/>
      <column name="DATE_EDIT" valueDate="2023-07-08T07:14:26"/>
      <column name="USE_TEMPLATE_ATTACHMENTS" valueNumeric="0"/>
      <column name="STATUS" value="BULKMAILNOTSENT"/>
    </insert>
    <insert tableName="BULKMAIL">
      <column name="SENDER_EMAIL_ADDRESS" value="meinefirma@adito.de"/>
      <column name="BULKMAILID" value="1f858970-2693-4c26-9899-949c195c81de"/>
      <column name="SUBJECT" value="Lead Nurturing: Infomail"/>
      <column name="MOSAICOTEMPLATE_ID" value="93d76a11-e391-45b6-8544-38a7ce164bd3"/>
      <column name="USER_EDIT" value="Lisa Sommer"/>
      <column name="SENDTYPE" value="SENDTYPE_MANUAL"/>
      <column name="USER_NEW" value="Lisa Sommer"/>
      <column name="INTEREST_ID" value="38c97136-9ea0-48f2-99e5-2bff9c2473c3"/>
      <column name="EMPLOYEE_CONTACT_ID" value="c7ddf982-0e58-4152-b82b-8f5673b0b729"/>
      <column name="DATE_NEW" valueDate="2023-06-12T11:49:09"/>
      <column name="CREATEACTIVITIES" valueNumeric="0"/>
      <column name="ISOLANGUAGE" value="deu"/>
      <column name="NAME" value="Lead Nurturing: Infomail"/>
      <column name="DATE_EDIT" valueDate="2023-06-13T12:41:31"/>
      <column name="USE_TEMPLATE_ATTACHMENTS" valueNumeric="0"/>
      <column name="STATUS" value="BULKMAILADHOC"/>
    </insert>
    <insert tableName="BULKMAIL">
      <column name="SENDER_EMAIL_ADDRESS" value="meinefirma@adito.de"/>
      <column name="BULKMAILID" value="21aa82a9-08ca-4651-8a29-c832bf011040"/>
      <column name="SUBJECT" value="Reminder: Kundentag bei meineFirma"/>
      <column name="PLACEOFUSE" value="Event"/>
      <column name="DESCRIPTION" value="(Mosaico-) Reminder zum Internen Kundentag."/>
      <column name="MOSAICOTEMPLATE_ID" value="f7350ac2-3df1-4482-880a-89415ce9a99c"/>
      <column name="DATE_TO_SEND" valueDate="2023-08-10T09:00:00"/>
      <column name="USER_EDIT" value="Admin"/>
      <column name="SENDTYPE" value="SENDTYPE_PLANNED"/>
      <column name="USER_NEW" value="Lisa Sommer"/>
      <column name="INTEREST_ID" value="2ad0e569-b9eb-4261-9cc7-4ed59e43a7ac"/>
      <column name="EMPLOYEE_CONTACT_ID" value="ef345d11-a40d-59e0-a24c-afcb6095d2cb"/>
      <column name="DATE_NEW" valueDate="2023-06-02T13:11:09"/>
      <column name="CREATEACTIVITIES" valueNumeric="0"/>
      <column name="ISOLANGUAGE" value="deu"/>
      <column name="NAME" value="meineFirma Kundentag (4): Reminder"/>
      <column name="DATE_EDIT" valueDate="2023-07-09T12:51:55"/>
      <column name="USE_TEMPLATE_ATTACHMENTS" valueNumeric="0"/>
      <column name="STATUS" value="BULKMAILNOTSENT"/>
    </insert>
    <insert tableName="BULKMAIL">
      <column name="SENDER_EMAIL_ADDRESS" value="meinefirma@adito.de"/>
      <column name="BULKMAILID" value="38e81d7e-9efa-4c45-a9a4-0f6ef012cc50"/>
      <column name="SUBJECT" value="Anmeldebestätigung: Kundentag bei meineFirma"/>
      <column name="PLACEOFUSE" value="Event"/>
      <column name="DESCRIPTION" value="(Mosaico-) Anmeldebestätigung zum Internen Kundentag. Eingeladen werden Geschäftsführer sowie andere Leitungs Positionen. "/>
      <column name="MOSAICOTEMPLATE_ID" value="4ddb23e2-5058-434c-b539-ead5fc25873f"/>
      <column name="USER_EDIT" value="Admin"/>
      <column name="SENDTYPE" value="SENDTYPE_MANUAL"/>
      <column name="USER_NEW" value="Admin"/>
      <column name="INTEREST_ID" value="2ad0e569-b9eb-4261-9cc7-4ed59e43a7ac"/>
      <column name="EMPLOYEE_CONTACT_ID" value="ef345d11-a40d-59e0-a24c-afcb6095d2cb"/>
      <column name="DATE_NEW" valueDate="2023-06-02T13:15:54"/>
      <column name="CREATEACTIVITIES" valueNumeric="0"/>
      <column name="ISOLANGUAGE" value="deu"/>
      <column name="NAME" value="meineFirma Kundentag (3): Bestätigung"/>
      <column name="DATE_EDIT" valueDate="2023-07-09T15:28:19"/>
      <column name="USE_TEMPLATE_ATTACHMENTS" valueNumeric="0"/>
      <column name="STATUS" value="BULKMAILADHOC"/>
    </insert>
    <insert tableName="BULKMAIL">
      <column name="SENDER_EMAIL_ADDRESS" value="meinefirma@adito.de"/>
      <column name="BULKMAILID" value="5867d781-ec36-49ae-be4f-d955b9e597d7"/>
      <column name="SUBJECT" value="Lead Nurturing: DOI Mail"/>
      <column name="MOSAICOTEMPLATE_ID" value="cbf07a31-9ef0-4510-9587-0a0e1ef3894d"/>
      <column name="USER_EDIT" value="Lisa Sommer"/>
      <column name="SENDTYPE" value="SENDTYPE_MANUAL"/>
      <column name="USER_NEW" value="Admin"/>
      <column name="INTEREST_ID" value="38c97136-9ea0-48f2-99e5-2bff9c2473c3"/>
      <column name="EMPLOYEE_CONTACT_ID" value="c7ddf982-0e58-4152-b82b-8f5673b0b729"/>
      <column name="DATE_NEW" valueDate="2023-06-12T11:48:09"/>
      <column name="CREATEACTIVITIES" valueNumeric="0"/>
      <column name="ISOLANGUAGE" value="deu"/>
      <column name="NAME" value="Lead Nurturing: DOI E-Mail"/>
      <column name="DATE_EDIT" valueDate="2023-06-13T12:40:54"/>
      <column name="USE_TEMPLATE_ATTACHMENTS" valueNumeric="0"/>
      <column name="STATUS" value="BULKMAILADHOC"/>
    </insert>
    <insert tableName="BULKMAIL">
      <column name="SENDER_EMAIL_ADDRESS" value="meinefirma@adito.de"/>
      <column name="BULKMAILID" value="6ffac366-a1ee-4cc2-b794-45a8698a928e"/>
      <column name="SUBJECT" value="Follow up: Kundentag bei meineFirma"/>
      <column name="PLACEOFUSE" value="Event"/>
      <column name="DESCRIPTION" value="(Mosaico-) Follow up zum Internen Kundentag. Eingeladen werden Geschäftsführer sowie andere Leitungs Positionen. "/>
      <column name="MOSAICOTEMPLATE_ID" value="75f66c60-1072-4ae0-bd9f-6baa960a7743"/>
      <column name="DATE_TO_SEND" valueDate="2023-07-09T14:30:00"/>
      <column name="USER_EDIT" value="Lisa Sommer"/>
      <column name="SENDTYPE" value="SENDTYPE_MANUAL"/>
      <column name="USER_NEW" value="Admin"/>
      <column name="INTEREST_ID" value="2ad0e569-b9eb-4261-9cc7-4ed59e43a7ac"/>
      <column name="EMPLOYEE_CONTACT_ID" value="ef345d11-a40d-59e0-a24c-afcb6095d2cb"/>
      <column name="DATE_NEW" valueDate="2023-06-02T13:11:50"/>
      <column name="CREATEACTIVITIES" valueNumeric="0"/>
      <column name="ISOLANGUAGE" value="deu"/>
      <column name="NAME" value="meineFirma Kundentag (5): Follow up"/>
      <column name="DATE_EDIT" valueDate="2023-07-09T15:35:20"/>
      <column name="USE_TEMPLATE_ATTACHMENTS" valueNumeric="0"/>
      <column name="STATUS" value="BULKMAILNOTSENT"/>
    </insert>
    <insert tableName="BULKMAIL">
      <column name="SENDER_EMAIL_ADDRESS" value="meinefirma@adito.de"/>
      <column name="BULKMAILID" value="97e91590-20e0-41c7-9da1-15959ad99a36"/>
      <column name="SUBJECT" value="Lead Nurturing: Reminder"/>
      <column name="MOSAICOTEMPLATE_ID" value="8fe56fdc-6cc0-4c23-8346-44cbfe9a5843"/>
      <column name="USER_EDIT" value="Lisa Sommer"/>
      <column name="SENDTYPE" value="SENDTYPE_MANUAL"/>
      <column name="USER_NEW" value="Admin"/>
      <column name="INTEREST_ID" value="38c97136-9ea0-48f2-99e5-2bff9c2473c3"/>
      <column name="EMPLOYEE_CONTACT_ID" value="c7ddf982-0e58-4152-b82b-8f5673b0b729"/>
      <column name="DATE_NEW" valueDate="2023-06-12T11:49:48"/>
      <column name="CREATEACTIVITIES" valueNumeric="0"/>
      <column name="ISOLANGUAGE" value="deu"/>
      <column name="NAME" value="Lead Nurturing: Reminder"/>
      <column name="DATE_EDIT" valueDate="2023-06-14T12:42:09"/>
      <column name="USE_TEMPLATE_ATTACHMENTS" valueNumeric="0"/>
      <column name="STATUS" value="BULKMAILADHOC"/>
    </insert>
    <insert tableName="BULKMAIL">
      <column name="SENDER_EMAIL_ADDRESS" value="meinefirma@adito.de"/>
      <column name="BULKMAILID" value="9e0c4f68-f9cc-4f19-9f8b-2a657419d4f6"/>
      <column name="SUBJECT" value="Save the date: Kundentag bei meineFirma"/>
      <column name="PLACEOFUSE" value="Event"/>
      <column name="DESCRIPTION" value="(Mosaico-) Save the date zum Internen Kundentag. Eingeladen werden Geschäftsführer sowie andere Leitungs Positionen. "/>
      <column name="MOSAICOTEMPLATE_ID" value="23c5c661-d82a-4af5-8103-15d29c014712"/>
      <column name="USER_EDIT" value="Lisa Sommer"/>
      <column name="SENDTYPE" value="SENDTYPE_MANUAL"/>
      <column name="USER_NEW" value="Admin"/>
      <column name="INTEREST_ID" value="2ad0e569-b9eb-4261-9cc7-4ed59e43a7ac"/>
      <column name="EMPLOYEE_CONTACT_ID" value="ef345d11-a40d-59e0-a24c-afcb6095d2cb"/>
      <column name="DATE_NEW" valueDate="2023-06-02T13:10:07"/>
      <column name="CREATEACTIVITIES" valueNumeric="0"/>
      <column name="ISOLANGUAGE" value="deu"/>
      <column name="NAME" value="meineFirma Kundentag (1): Save the date"/>
      <column name="DATE_EDIT" valueDate="2023-06-07T14:00:00"/>
      <column name="USE_TEMPLATE_ATTACHMENTS" valueNumeric="0"/>
      <column name="STATUS" value="BULKMAILSENT"/>
    </insert>
    <insert tableName="BULKMAIL">
      <column name="SENDER_EMAIL_ADDRESS" value="meinefirma@adito.de"/>
      <column name="BULKMAILID" value="9fd17ec8-9743-472c-9c15-b02954d7fd37"/>
      <column name="SUBJECT" value="meine Firma News: Sommer, Sonne"/>
      <column name="DESCRIPTION" value="(Mosaico-) Newsletter Sommer, Sonne"/>
      <column name="MOSAICOTEMPLATE_ID" value="7bd0f2f9-7e21-478b-a868-853529ecd785"/>
      <column name="USER_EDIT" value="Lisa Sommer"/>
      <column name="SENDTYPE" value="SENDTYPE_MANUAL"/>
      <column name="USER_NEW" value="Lisa Sommer"/>
      <column name="INTEREST_ID" value="6dd7cee1-5103-4086-8291-c29176c7b082"/>
      <column name="EMPLOYEE_CONTACT_ID" value="ef345d11-a40d-59e0-a24c-afcb6095d2cb"/>
      <column name="DATE_NEW" valueDate="2023-06-13T14:49:47"/>
      <column name="CREATEACTIVITIES" valueNumeric="0"/>
      <column name="ISOLANGUAGE" value="deu"/>
      <column name="NAME" value="meineFirma Newsletter"/>
      <column name="DATE_EDIT" valueDate="2023-07-04T14:10:48"/>
      <column name="USE_TEMPLATE_ATTACHMENTS" valueNumeric="0"/>
      <column name="STATUS" value="BULKMAILSENT"/>
    </insert>
    <insert tableName="BULKMAIL">
      <column name="SENDER_EMAIL_ADDRESS" value="meinefirma@adito.de"/>
      <column name="BULKMAILID" value="b46a5ed5-fd73-4f07-91d5-9dc8636b5213"/>
      <column name="SUBJECT" value="Wartebenachrichtigung: Kundentag bei meineFirma"/>
      <column name="PLACEOFUSE" value="Event"/>
      <column name="DESCRIPTION" value="(Mosaico-) Wartebenachrichtigung zum Internen Kundentag. Wird bei der Abmeldung und überschreiten der max. Teilnehmerzahl automatisch versendet."/>
      <column name="MOSAICOTEMPLATE_ID" value="6232b598-6302-440c-8d1d-9102bd9ea54f"/>
      <column name="USER_EDIT" value="Admin"/>
      <column name="SENDTYPE" value="SENDTYPE_MANUAL"/>
      <column name="USER_NEW" value="Admin"/>
      <column name="INTEREST_ID" value="2ad0e569-b9eb-4261-9cc7-4ed59e43a7ac"/>
      <column name="EMPLOYEE_CONTACT_ID" value="c7ddf982-0e58-4152-b82b-8f5673b0b729"/>
      <column name="DATE_NEW" valueDate="2023-07-08T17:14:22"/>
      <column name="CREATEACTIVITIES" valueNumeric="0"/>
      <column name="ISOLANGUAGE" value="deu"/>
      <column name="NAME" value="meineFirma Kundentag (3b): Wartebenachrichtigung"/>
      <column name="DATE_EDIT" valueDate="2023-07-08T17:18:41"/>
      <column name="USE_TEMPLATE_ATTACHMENTS" valueNumeric="0"/>
      <column name="STATUS" value="BULKMAILADHOC"/>
    </insert>
    <insert tableName="BULKMAIL">
      <column name="SENDER_EMAIL_ADDRESS" value="meinefirma@adito.de"/>
      <column name="BULKMAILID" value="b846ae15-d846-4278-a09b-f2ecc8cd0106"/>
      <column name="SUBJECT" value="Einladung: Kundentag bei meineFirma"/>
      <column name="PLACEOFUSE" value="Event"/>
      <column name="DESCRIPTION" value="(Mosaico-) Einladungsschreiben zum Internen Kundentag. Eingeladen werden Geschäftsführer sowie andere Leitungs Positionen. "/>
      <column name="MOSAICOTEMPLATE_ID" value="0d0b8fa8-3452-4fcf-9877-91a32d810f46"/>
      <column name="USER_EDIT" value="Lisa Sommer"/>
      <column name="SENDTYPE" value="SENDTYPE_MANUAL"/>
      <column name="INTEREST_ID" value="2ad0e569-b9eb-4261-9cc7-4ed59e43a7ac"/>
      <column name="EMPLOYEE_CONTACT_ID" value="ef345d11-a40d-59e0-a24c-afcb6095d2cb"/>
      <column name="CREATEACTIVITIES" valueNumeric="0"/>
      <column name="ISOLANGUAGE" value="deu"/>
      <column name="NAME" value="meineFirma Kundentag (2): Einladung"/>
      <column name="DATE_EDIT" valueDate="2023-07-09T15:00:00"/>
      <column name="USE_TEMPLATE_ATTACHMENTS" valueNumeric="0"/>
      <column name="STATUS" value="BULKMAILSENT"/>
    </insert>
    <insert tableName="BULKMAIL">
      <column name="SENDER_EMAIL_ADDRESS" value="meinefirma@adito.de"/>
      <column name="BULKMAILID" value="c1e7a941-2ab3-4954-b206-48b8dc3d77af"/>
      <column name="SUBJECT" value="Erstkontakt mit meineFirma"/>
      <column name="DESCRIPTION" value="Serienmail, um unseren Interessenten - Firmen/Kontakte - unser Unternehmen zu präsentieren"/>
      <column name="USER_EDIT" value="Admin"/>
      <column name="SENDTYPE" value="SENDTYPE_MANUAL"/>
      <column name="INTEREST_ID" value="38c97136-9ea0-48f2-99e5-2bff9c2473c3"/>
      <column name="EMPLOYEE_CONTACT_ID" value="ef345d11-a40d-59e0-a24c-afcb6095d2cb"/>
      <column name="DATE_NEW" valueDate="2023-06-19T13:24:14"/>
      <column name="CREATEACTIVITIES" valueNumeric="1"/>
      <column name="ISOLANGUAGE" value="deu"/>
      <column name="DOCUMENTTEMPLATE_ID" value="d5b13c3e-64c2-4978-a726-1bfaed6eff09"/>
      <column name="NAME" value="Unternehmenspräsentation"/>
      <column name="DATE_EDIT" valueDate="2023-07-08T13:24:14"/>
      <column name="USE_TEMPLATE_ATTACHMENTS" valueNumeric="1"/>
      <column name="STATUS" value="BULKMAILNOTSENT"/>
    </insert>
    <insert tableName="BULKMAIL">
      <column name="SENDER_EMAIL_ADDRESS" value="meinefirma@adito.de"/>
      <column name="BULKMAILID" value="f0e6f096-d392-4ae2-87f2-b804cd3aec75"/>
      <column name="SUBJECT" value="Geänderte AGB"/>
      <column name="DESCRIPTION" value="Serienmail, um unsere Kunden über die geänderten AGB zu informieren. Der aktuelle Stand der AGB wird als Anhang versendet.&#10;Es wird bei jedem Empfänger eine Aktivität angelegt."/>
      <column name="USER_EDIT" value="Admin"/>
      <column name="SENDTYPE" value="SENDTYPE_MANUAL"/>
      <column name="INTEREST_ID" value="f22a75f9-bec6-4dd5-8ba0-357218d73099"/>
      <column name="EMPLOYEE_CONTACT_ID" value="a2e084e2-d68a-4f1e-a1bb-f8d46ad6293d"/>
      <column name="DATE_NEW" valueDate="2023-06-19T12:14:14"/>
      <column name="CREATEACTIVITIES" valueNumeric="1"/>
      <column name="ISOLANGUAGE" value="deu"/>
      <column name="DOCUMENTTEMPLATE_ID" value="5211f38d-a6c1-4327-bb3f-c0963e89e7b4"/>
      <column name="NAME" value="Mitteilung über Änderung der AGB"/>
      <column name="DATE_EDIT" valueDate="2023-07-08T12:30:10"/>
      <column name="USE_TEMPLATE_ATTACHMENTS" valueNumeric="1"/>
      <column name="STATUS" value="BULKMAILNOTSENT"/>
    </insert>
  </changeSet>
</databaseChangeLog>