<?xml version="1.1" encoding="UTF-8" standalone="no"?>
<databaseChangeLog xmlns="http://www.liquibase.org/xml/ns/dbchangelog" xmlns:ext="http://www.liquibase.org/xml/ns/dbchangelog-ext" xmlns:xsi="http://www.w3.org/2001/XMLSchema-instance" xsi:schemaLocation="http://www.liquibase.org/xml/ns/dbchangelog-ext http://www.liquibase.org/xml/ns/dbchangelog/dbchangelog-ext.xsd http://www.liquibase.org/xml/ns/dbchangelog http://www.liquibase.org/xml/ns/dbchangelog/dbchangelog-3.6.xsd">
  <changeSet author="autogenerated" id="45409fd9-ab8f-4474-ada5-d8bc9a968f7b">
    <delete tableName="EVENT"/>
    <insert tableName="EVENT">
      <column name="EVENTID" value="4eefebe6-ec60-4ffe-98e0-7a7e9be9fa1e"/>
      <column name="EVENTCODE" valueNumeric="1001"/>
      <column name="REGISTRATION_DEADLINE" valueDate="2023-10-31T12:00:00"/>
      <column name="MAXPARTICIPANTS" valueNumeric="25"/>
      <column name="DESCRIPTION" value="Seminarinhalte:&#10;Kennenlernen der neuen Produkte&#10;Einsatz der neuen Präsentationsmaterialien&#10;Training &quot;Neue Produkte im Kundengespräch präsentieren&quot;"/>
      <column name="USER_EDIT" value="Admin"/>
      <column name="TYPE" value="TRAINING"/>
      <column name="USER_NEW" value="Admin"/>
      <column name="EMPLOYEE_CONTACT_ID" value="c7ddf982-0e58-4152-b82b-8f5673b0b729"/>
      <column name="DATE_NEW" valueDate="2023-07-08T05:52:28"/>
      <column name="EVENT_END" valueDate="2023-11-04T15:15:00"/>
      <column name="NAME" value="Seminar"/>
      <column name="DATE_EDIT" valueDate="2023-07-16T10:24:00"/>
      <column name="LOCATION" value="Videokonferenzsystem"/>
      <column name="EVENT_BEGIN" valueDate="2023-11-04T07:00:00"/>
      <column name="STATUS" value="PLANNING"/>
    </insert>
    <insert tableName="EVENT">
      <column name="EVENTID" value="597e2bcb-86f2-4229-bf9f-736ddcafd956"/>
      <column name="EVENTCODE" valueNumeric="1002"/>
      <column name="REGISTRATION_DEADLINE" valueDate="2023-10-27T12:00:00"/>
      <column name="MAXPARTICIPANTS" valueNumeric="100"/>
      <column name="DESCRIPTION" value="Wie verändert sich Zusammenarbeit in Zukunft? Welche Plattform-Technologien sind dafür relevant? Welche Rolle spielt dabei Agilität? Das erfahrst du im Webinar."/>
      <column name="USER_EDIT" value="Admin"/>
      <column name="TYPE" value="WEBINAR"/>
      <column name="USER_NEW" value="Admin"/>
      <column name="EMPLOYEE_CONTACT_ID" value="c7ddf982-0e58-4152-b82b-8f5673b0b729"/>
      <column name="DATE_NEW" valueDate="2023-07-07T12:42:28"/>
      <column name="EVENT_END" valueDate="2023-10-28T09:00:00"/>
      <column name="NAME" value="Zusammenarbeit der Zukunft"/>
      <column name="DATE_EDIT" valueDate="2023-07-16T11:15:51"/>
      <column name="EVENT_BEGIN" valueDate="2023-10-28T08:00:00"/>
      <column name="STATUS" value="PLANNING"/>
    </insert>
    <insert tableName="EVENT">
      <column name="EVENTID" value="fdc44318-7315-48ce-b276-e3e967783112"/>
      <column name="EVENTCODE" valueNumeric="1000"/>
      <column name="REGISTRATION_DEADLINE" valueDate="2023-08-12T12:00:00"/>
      <column name="MAXPARTICIPANTS" valueNumeric="100"/>
      <column name="DESCRIPTION" value="Wir möchten dir und unseren Besuchern den größten Mehrwert bieten und gerne erfahren, ob du Vor-Ort-Events mit Wissenstransfer, guten Gesprächen, lockerer Atmosphäre und Abendveranstaltung genauso sehr vermisst wie wir.&#10;&#10;"/>
      <column name="USER_EDIT" value="Admin"/>
      <column name="TYPE" value="INHOUSE"/>
      <column name="USER_NEW" value="Admin"/>
      <column name="EMPLOYEE_CONTACT_ID" value="c7ddf982-0e58-4152-b82b-8f5673b0b729"/>
      <column name="DATE_NEW" valueDate="2023-07-02T01:06:06"/>
      <column name="EVENT_END" valueDate="2023-08-29T19:30:00"/>
      <column name="NAME" value="meineFirma Kundentag"/>
      <column name="DATE_EDIT" valueDate="2023-07-14T07:00:21"/>
      <column name="EVENT_BEGIN" valueDate="2023-08-29T09:00:00"/>
      <column name="STATUS" value="APPROVED"/>
    </insert>
  </changeSet>
</databaseChangeLog>