<?xml version="1.1" encoding="UTF-8" standalone="no"?>
<databaseChangeLog xmlns="http://www.liquibase.org/xml/ns/dbchangelog" xmlns:ext="http://www.liquibase.org/xml/ns/dbchangelog-ext" xmlns:xsi="http://www.w3.org/2001/XMLSchema-instance" xsi:schemaLocation="http://www.liquibase.org/xml/ns/dbchangelog-ext http://www.liquibase.org/xml/ns/dbchangelog/dbchangelog-ext.xsd http://www.liquibase.org/xml/ns/dbchangelog http://www.liquibase.org/xml/ns/dbchangelog/dbchangelog-3.6.xsd">
  <changeSet author="autogenerated" id="0ecb68a9-d1f4-4222-8404-0037e5838ccb">
    <delete tableName="MAIL_RUN"/>
    <insert tableName="MAIL_RUN">
      <column name="OBJECT_TYPE" value="Bulkmail"/>
      <column name="MAIL_RUNID" value="51896e9e-6806-465b-9436-04556df4dff5"/>
      <column name="DATE_RUN_START" valueDate="2023-06-14T06:45:43"/>
      <column name="TESTRUN" valueNumeric="0"/>
      <column name="DATE_RUN_FINISHED" valueDate="2023-06-14T06:45:44"/>
      <column name="OBJECT_ROWID" value="5867d781-ec36-49ae-be4f-d955b9e597d7"/>
      <column name="STATUS" value="BULKMAILSENT"/>
    </insert>
    <insert tableName="MAIL_RUN">
      <column name="OBJECT_TYPE" value="Bulkmail"/>
      <column name="MAIL_RUNID" value="7275b6ac-529b-4e81-91fe-1236898c42df"/>
      <column name="DATE_RUN_START" valueDate="2023-06-07T14:00:24"/>
      <column name="TESTRUN" valueNumeric="0"/>
      <column name="DATE_RUN_FINISHED" valueDate="2023-06-07T14:01:31"/>
      <column name="OBJECT_ROWID" value="9e0c4f68-f9cc-4f19-9f8b-2a657419d4f6"/>
      <column name="STATUS" value="BULKMAILSENT"/>
    </insert>
    <insert tableName="MAIL_RUN">
      <column name="OBJECT_TYPE" value="Bulkmail"/>
      <column name="MAIL_RUNID" value="8b6cc954-1a59-4f45-8c3b-2f76de945818"/>
      <column name="DATE_RUN_START" valueDate="2023-07-09T15:00:58"/>
      <column name="TESTRUN" valueNumeric="0"/>
      <column name="DATE_RUN_FINISHED" valueDate="2023-07-09T15:02:03"/>
      <column name="OBJECT_ROWID" value="b846ae15-d846-4278-a09b-f2ecc8cd0106"/>
      <column name="STATUS" value="BULKMAILSENT"/>
    </insert>
    <insert tableName="MAIL_RUN">
      <column name="OBJECT_TYPE" value="Bulkmail"/>
      <column name="MAIL_RUNID" value="8d353d5e-07df-43ec-a7ba-59392ba0e0e8"/>
      <column name="DATE_RUN_START" valueDate="2023-07-04T14:16:29"/>
      <column name="TESTRUN" valueNumeric="1"/>
      <column name="DATE_RUN_FINISHED" valueDate="2023-07-04T14:16:30"/>
      <column name="OBJECT_ROWID" value="9fd17ec8-9743-472c-9c15-b02954d7fd37"/>
      <column name="STATUS" value="BULKMAILSENT"/>
    </insert>
    <insert tableName="MAIL_RUN">
      <column name="OBJECT_TYPE" value="Bulkmail"/>
      <column name="MAIL_RUNID" value="9d01b267-de62-444a-9b95-640ebeb774f2"/>
      <column name="DATE_RUN_START" valueDate="2023-06-27T06:48:09"/>
      <column name="TESTRUN" valueNumeric="0"/>
      <column name="DATE_RUN_FINISHED" valueDate="2023-06-27T06:48:09"/>
      <column name="OBJECT_ROWID" value="97e91590-20e0-41c7-9da1-15959ad99a36"/>
      <column name="STATUS" value="BULKMAILSENT"/>
    </insert>
    <insert tableName="MAIL_RUN">
      <column name="OBJECT_TYPE" value="Bulkmail"/>
      <column name="MAIL_RUNID" value="a676eb2a-baee-4eb5-aa62-05fa9d33c2f3"/>
      <column name="DATE_RUN_START" valueDate="2023-07-04T14:16:40"/>
      <column name="TESTRUN" valueNumeric="0"/>
      <column name="DATE_RUN_FINISHED" valueDate="2023-07-04T14:16:41"/>
      <column name="OBJECT_ROWID" value="9fd17ec8-9743-472c-9c15-b02954d7fd37"/>
      <column name="STATUS" value="BULKMAILSENT"/>
    </insert>
    <insert tableName="MAIL_RUN">
      <column name="OBJECT_TYPE" value="Bulkmail"/>
      <column name="MAIL_RUNID" value="ec18ab99-aa26-473d-9731-6410abf52df8"/>
      <column name="DATE_RUN_START" valueDate="2023-06-14T08:46:59"/>
      <column name="TESTRUN" valueNumeric="0"/>
      <column name="DATE_RUN_FINISHED" valueDate="2023-06-14T08:46:59"/>
      <column name="OBJECT_ROWID" value="1f858970-2693-4c26-9899-949c195c81de"/>
      <column name="STATUS" value="BULKMAILSENT"/>
    </insert>
  </changeSet>
</databaseChangeLog>