<?xml version="1.1" encoding="UTF-8" standalone="no"?>
<databaseChangeLog xmlns="http://www.liquibase.org/xml/ns/dbchangelog" xmlns:ext="http://www.liquibase.org/xml/ns/dbchangelog-ext" xmlns:xsi="http://www.w3.org/2001/XMLSchema-instance" xsi:schemaLocation="http://www.liquibase.org/xml/ns/dbchangelog-ext http://www.liquibase.org/xml/ns/dbchangelog/dbchangelog-ext.xsd http://www.liquibase.org/xml/ns/dbchangelog http://www.liquibase.org/xml/ns/dbchangelog/dbchangelog-3.6.xsd">
  <changeSet author="autogenerated" id="6ad8523b-4648-4fe5-9301-370d1bc54f83">
    <delete tableName="ORGANISATION"/>
    <insert tableName="ORGANISATION">
      <column name="ORGANISATIONID" value="0                                   "/>
      <column name="KIND" value="ORGCUTOMER"/>
      <column name="NAME" value="privat"/>
      <column name="USER_NEW" value="Admin"/>
      <column name="DATE_NEW" valueDate="2021-05-22T02:42:44"/>
    </insert>
    <insert tableName="ORGANISATION">
      <column name="ORGANISATIONID" value="03e09527-21cc-489a-b37f-0dd7df553c20"/>
      <column name="KIND" value="ORGPROSPECT"/>
      <column name="NAME" value="Lichtenstein Document Solutions GmbH"/>
      <column name="DATE_EDIT" valueDate="2023-03-22T12:46:24"/>
      <column name="CUSTOMERCODE" value="2419"/>
      <column name="USER_EDIT" value="Admin"/>
      <column name="USER_NEW" value="Admin"/>
      <column name="PICTURE" valueBlobFile="ORGANISATION/PICTURE/blobFiles/99de066ed32cd02b3a171c324848ffe9"/>
      <column name="DATE_NEW" valueDate="2021-02-03T01:16:04"/>
    </insert>
    <insert tableName="ORGANISATION">
      <column name="ORGANISATIONID" value="06006801-c6a1-4321-9fde-95f9d3f9b786"/>
      <column name="KIND" value="ORGTYPEOTHER"/>
      <column name="NAME" value="meineFirma GmbH"/>
      <column name="DATE_EDIT" valueDate="2023-09-08T10:59:25"/>
      <column name="CUSTOMERCODE" value="0001"/>
      <column name="USER_EDIT" value="Admin"/>
      <column name="USER_NEW" value="Admin"/>
      <column name="PICTURE" valueBlobFile="ORGANISATION/PICTURE/blobFiles/e8e99147833a5fd420f10f9ae0658153"/>
      <column name="DATE_NEW" valueDate="2021-02-03T01:16:04"/>
    </insert>
    <insert tableName="ORGANISATION">
      <column name="ORGANISATIONID" value="061ab1bb-b7cd-4408-a7f4-e863d70411a9"/>
      <column name="KIND" value="ORGCUTOMER"/>
      <column name="NAME" value="Anderson-Dibbert"/>
      <column name="DATE_EDIT" valueDate="2023-03-23T08:29:19"/>
      <column name="CUSTOMERCODE" value="1672"/>
      <column name="USER_EDIT" value="Admin"/>
      <column name="USER_NEW" value="Birgit Leicht"/>
      <column name="DATE_NEW" valueDate="2023-03-22T03:02:51"/>
    </insert>
    <insert tableName="ORGANISATION">
      <column name="ORGANISATIONID" value="09281be8-8cb5-4201-9758-8c86b3d2bb85"/>
      <column name="KIND" value="ORGCUTOMER"/>
      <column name="NAME" value="Grobbe-Werk GmbH"/>
      <column name="DATE_EDIT" valueDate="2023-03-22T12:40:16"/>
      <column name="CUSTOMERCODE" value="4758"/>
      <column name="USER_EDIT" value="Admin"/>
      <column name="USER_NEW" value="Admin"/>
      <column name="PICTURE" valueBlobFile="ORGANISATION/PICTURE/blobFiles/ca72b7a7f328a50860b5660a81e79112"/>
      <column name="DATE_NEW" valueDate="2021-02-07T09:47:27"/>
    </insert>
    <insert tableName="ORGANISATION">
      <column name="ORGANISATIONID" value="1                                   "/>
      <column name="KIND" value="ORGCUTOMER"/>
      <column name="NAME" value="DSGVO-Anonymisierung"/>
      <column name="USER_NEW" value="Admin"/>
      <column name="DATE_NEW" valueDate="2023-03-03T10:47:53"/>
    </insert>
    <insert tableName="ORGANISATION">
      <column name="ORGANISATIONID" value="125cbb66-fe0a-4ecf-8be0-d9bec61dbe53"/>
      <column name="KIND" value="ORGPROSPECT"/>
      <column name="NAME" value="Bohrmarkt GmbH"/>
      <column name="DATE_EDIT" valueDate="2023-07-09T08:24:17"/>
      <column name="CUSTOMERCODE" value="9612"/>
      <column name="USER_EDIT" value="Lisa Sommer"/>
      <column name="USER_NEW" value="Admin"/>
      <column name="INFO" value="Größere Baumarktkette"/>
      <column name="DATE_NEW" valueDate="2023-09-08T09:38:59"/>
    </insert>
    <insert tableName="ORGANISATION">
      <column name="ORGANISATIONID" value="13e60843-5d6d-45ee-88c7-46db41874138"/>
      <column name="KIND" value="ORGCUTOMER"/>
      <column name="NAME" value="Firmengruppe Matthias Bogen"/>
      <column name="DATE_EDIT" valueDate="2023-03-22T12:39:50"/>
      <column name="CUSTOMERCODE" value="4567"/>
      <column name="USER_EDIT" value="Admin"/>
      <column name="USER_NEW" value="Admin"/>
      <column name="PICTURE" valueBlobFile="ORGANISATION/PICTURE/blobFiles/f6c1847fc1d106d0a10cc772b135abeb"/>
      <column name="DATE_NEW" valueDate="2021-02-07T09:59:37"/>
    </insert>
    <insert tableName="ORGANISATION">
      <column name="ORGANISATIONID" value="1ca7a2a1-68fd-475c-aac6-79d7b42d0514"/>
      <column name="KIND" value="ORGPROSPECT"/>
      <column name="NAME" value="Hochbau Berger"/>
      <column name="CUSTOMERCODE" value="8364"/>
      <column name="USER_NEW" value="Admin"/>
      <column name="DATE_NEW" valueDate="2023-09-08T09:48:45"/>
    </insert>
    <insert tableName="ORGANISATION">
      <column name="ORGANISATIONID" value="22f1ca45-e633-4080-9d5c-9a8c2e06d3f9"/>
      <column name="KIND" value="ORGCUTOMER"/>
      <column name="NAME" value="JPM Touristik GmbH"/>
      <column name="DATE_EDIT" valueDate="2023-03-22T12:40:49"/>
      <column name="CUSTOMERCODE" value="4545"/>
      <column name="USER_EDIT" value="Admin"/>
      <column name="USER_NEW" value="Admin"/>
      <column name="PICTURE" valueBlobFile="ORGANISATION/PICTURE/blobFiles/d8a054cf70fd6db2fd8f58ab6aecd1a9"/>
      <column name="DATE_NEW" valueDate="2021-02-07T09:40:19"/>
    </insert>
    <insert tableName="ORGANISATION">
      <column name="ORGANISATIONID" value="2c63e0de-f21c-474f-89d7-bff8ba1dbf43"/>
      <column name="KIND" value="ORGCUTOMER"/>
      <column name="NAME" value="Industrial Steel AG"/>
      <column name="DATE_EDIT" valueDate="2022-05-17T09:25:02"/>
      <column name="CUSTOMERCODE" value="1234"/>
      <column name="USER_EDIT" value="Admin"/>
      <column name="USER_NEW" value="Admin"/>
      <column name="PICTURE" valueBlobFile="ORGANISATION/PICTURE/blobFiles/e52da34403680e373472df5a8722981b"/>
      <column name="INFO" value="Die Industrial Steel AG ist einer der führenden Stahlhersteller weltweit. Das Unternehmen agiert mit über 5.000 Mitarbeitern in über 32 Ländern. "/>
      <column name="DATE_NEW" valueDate="2021-02-05T03:16:26"/>
    </insert>
    <insert tableName="ORGANISATION">
      <column name="ORGANISATIONID" value="303335a9-6c93-4130-8d2b-7fda679d1d8e"/>
      <column name="NAME" value="Seven "/>
      <column name="USER_NEW" value="Admin"/>
      <column name="DATE_NEW" valueDate="2023-07-11T11:52:02"/>
    </insert>
    <insert tableName="ORGANISATION">
      <column name="ORGANISATIONID" value="35156003-d921-4a48-9d17-febfcbe0a78d"/>
      <column name="KIND" value="ORGCUTOMER"/>
      <column name="NAME" value="Holzwurm Maschinen GmbH"/>
      <column name="CUSTOMERCODE" value="5690"/>
      <column name="USER_NEW" value="Admin"/>
      <column name="DATE_NEW" valueDate="2023-09-08T09:51:16"/>
    </insert>
    <insert tableName="ORGANISATION">
      <column name="ORGANISATIONID" value="398b0b52-b0e2-4b8f-9ca3-f231ebf169b6"/>
      <column name="KIND" value="ORGPROSPECT"/>
      <column name="NAME" value="Lugner AG"/>
      <column name="DATE_EDIT" valueDate="2023-09-08T10:59:44"/>
      <column name="CUSTOMERCODE" value="5469"/>
      <column name="USER_EDIT" value="Admin"/>
      <column name="USER_NEW" value="Admin"/>
      <column name="PICTURE" valueBlobFile="ORGANISATION/PICTURE/blobFiles/e44649421a92ff00e800fe8c0a3cfa15"/>
      <column name="DATE_NEW" valueDate="2023-09-08T09:31:55"/>
    </insert>
    <insert tableName="ORGANISATION">
      <column name="ORGANISATIONID" value="3b881135-b20e-4e2c-8fb4-b74ab430a3b1"/>
      <column name="KIND" value="ORGCUTOMER"/>
      <column name="NAME" value="Lockman LLC"/>
      <column name="DATE_EDIT" valueDate="2023-03-23T08:23:47"/>
      <column name="CUSTOMERCODE" value="1591"/>
      <column name="USER_EDIT" value="Admin"/>
      <column name="USER_NEW" value="Birgit Leicht"/>
      <column name="DATE_NEW" valueDate="2023-03-22T02:47:14"/>
    </insert>
    <insert tableName="ORGANISATION">
      <column name="ORGANISATIONID" value="3d050105-502a-4d0b-9eb4-6d9e8d8ad965"/>
      <column name="KIND" value="ORGPROSPECT"/>
      <column name="NAME" value="Kran und Kollegen KG"/>
      <column name="CUSTOMERCODE" value="7727"/>
      <column name="USER_NEW" value="Admin"/>
      <column name="DATE_NEW" valueDate="2023-09-08T09:43:31"/>
    </insert>
    <insert tableName="ORGANISATION">
      <column name="ORGANISATIONID" value="4b300326-ac41-40a6-a825-1ffe1bc0b196"/>
      <column name="KIND" value="ORGPROSPECT"/>
      <column name="NAME" value="Magic Gray"/>
      <column name="CUSTOMERCODE" value="5589"/>
      <column name="USER_NEW" value="Lisa Sommer"/>
      <column name="DATE_NEW" valueDate="2023-07-08T11:42:32"/>
    </insert>
    <insert tableName="ORGANISATION">
      <column name="ORGANISATIONID" value="533edbca-0838-4fe0-b2a0-eea3463bcaea"/>
      <column name="KIND" value="ORGPROSPECT"/>
      <column name="NAME" value="Tri Bau GmbH"/>
      <column name="DATE_EDIT" valueDate="2023-07-11T09:01:43"/>
      <column name="CUSTOMERCODE" value="9369"/>
      <column name="USER_EDIT" value="Admin"/>
      <column name="USER_NEW" value="Admin"/>
      <column name="DATE_NEW" valueDate="2023-09-08T09:36:23"/>
    </insert>
    <insert tableName="ORGANISATION">
      <column name="ORGANISATIONID" value="62175b31-b432-4ec6-932f-8e69033884c6"/>
      <column name="KIND" value="ORGPROSPECT"/>
      <column name="NAME" value="Kronen AG"/>
      <column name="DATE_EDIT" valueDate="2023-03-22T12:41:04"/>
      <column name="CUSTOMERCODE" value="5874"/>
      <column name="USER_EDIT" value="Admin"/>
      <column name="USER_NEW" value="Admin"/>
      <column name="PICTURE" valueBlobFile="ORGANISATION/PICTURE/blobFiles/3d95ffce5a6e8f603945969f5e14574c"/>
      <column name="DATE_NEW" valueDate="2021-02-07T09:38:43"/>
    </insert>
    <insert tableName="ORGANISATION">
      <column name="ORGANISATIONID" value="630c0384-412c-40e1-8c4f-2e0aa4e7ab25"/>
      <column name="KIND" value="ORGPROSPECT"/>
      <column name="NAME" value="Brandt Feldmann AG"/>
      <column name="DATE_EDIT" valueDate="2023-03-23T08:29:57"/>
      <column name="CUSTOMERCODE" value="1674"/>
      <column name="USER_EDIT" value="Admin"/>
      <column name="USER_NEW" value="Birgit Leicht"/>
      <column name="DATE_NEW" valueDate="2023-03-22T03:29:49"/>
    </insert>
    <insert tableName="ORGANISATION">
      <column name="ORGANISATIONID" value="692e1f81-9f05-4e22-b74d-56d34c671067"/>
      <column name="KIND" value="ORGCUTOMER"/>
      <column name="NAME" value="Glob Group"/>
      <column name="DATE_EDIT" valueDate="2023-03-22T02:14:23"/>
      <column name="CUSTOMERCODE" value="1212"/>
      <column name="USER_EDIT" value="Birgit Leicht"/>
      <column name="USER_NEW" value="Admin"/>
      <column name="PICTURE" valueBlobFile="ORGANISATION/PICTURE/blobFiles/e0644a2667e3c3d61d8f0b1e213b593d"/>
      <column name="DATE_NEW" valueDate="2021-02-13T10:52:35"/>
    </insert>
    <insert tableName="ORGANISATION">
      <column name="ORGANISATIONID" value="6a92df58-2b98-40da-ba6a-d0ddb1fde234"/>
      <column name="KIND" value="ORGCUTOMER"/>
      <column name="NAME" value="Transatlantik Logistics GmbH"/>
      <column name="DATE_EDIT" valueDate="2023-03-22T01:01:31"/>
      <column name="CUSTOMERCODE" value="1235"/>
      <column name="USER_EDIT" value="Admin"/>
      <column name="USER_NEW" value="Admin"/>
      <column name="PICTURE" valueBlobFile="ORGANISATION/PICTURE/blobFiles/d9f4a716ee8c1b45ab334b83e2725ac8"/>
      <column name="INFO" value="Die Transatlantik Logistic Gruppe ist ein Zusammenschluss aus mehreren Logistik Unternehmen.  Über 3.000 Mitarbeiter sind bei dem europäischen Logistikriesen beschäftigt. "/>
      <column name="DATE_NEW" valueDate="2021-02-05T03:22:41"/>
    </insert>
    <insert tableName="ORGANISATION">
      <column name="ORGANISATIONID" value="7534614c-578f-4df3-abf5-a6701989994a"/>
      <column name="KIND" value="ORGPROSPECT"/>
      <column name="NAME" value="Mars Elektronik GmbH "/>
      <column name="DATE_EDIT" valueDate="2023-09-08T12:14:22"/>
      <column name="CUSTOMERCODE" value="6602"/>
      <column name="USER_EDIT" value="Admin"/>
      <column name="USER_NEW" value="Admin"/>
      <column name="DATE_NEW" valueDate="2023-09-08T09:29:59"/>
    </insert>
    <insert tableName="ORGANISATION">
      <column name="ORGANISATIONID" value="756662b5-f5e4-479c-8d97-abd6a395bd79"/>
      <column name="KIND" value="ORGMANUF"/>
      <column name="NAME" value="Aquire GmbH"/>
      <column name="DATE_EDIT" valueDate="2023-03-22T12:38:40"/>
      <column name="CUSTOMERCODE" value="3469"/>
      <column name="USER_EDIT" value="Admin"/>
      <column name="USER_NEW" value="Admin"/>
      <column name="PICTURE" valueBlobFile="ORGANISATION/PICTURE/blobFiles/810b901d506b408e30aaa2e83b50c285"/>
      <column name="DATE_NEW" valueDate="2021-02-07T10:02:40"/>
    </insert>
    <insert tableName="ORGANISATION">
      <column name="ORGANISATIONID" value="77680f1e-9514-41c2-96fa-b8de4116f7e3"/>
      <column name="KIND" value="ORGPROSPECT"/>
      <column name="NAME" value="Schäferland Handelswelt GmbH "/>
      <column name="DATE_EDIT" valueDate="2023-09-08T12:16:01"/>
      <column name="CUSTOMERCODE" value="7732"/>
      <column name="USER_EDIT" value="Admin"/>
      <column name="USER_NEW" value="Admin"/>
      <column name="INFO" value="Vertrieb und Handel von Spielzeugwaren. &#10;Unternehmen besteht seit 1937 in mittlerweile 2. Generation. &#10;24 Standorte in Deutschland und Shop-in-Shop-Systeme. "/>
      <column name="DATE_NEW" valueDate="2023-09-08T09:41:22"/>
    </insert>
    <insert tableName="ORGANISATION">
      <column name="ORGANISATIONID" value="7ddd46b1-9e2b-4969-9b07-71b5369050e1"/>
      <column name="KIND" value="ORGPROSPECT"/>
      <column name="NAME" value="Rixner und Rupp SE"/>
      <column name="DATE_EDIT" valueDate="2023-09-08T10:38:06"/>
      <column name="CUSTOMERCODE" value="4945"/>
      <column name="USER_EDIT" value="Admin"/>
      <column name="USER_NEW" value="Admin"/>
      <column name="PICTURE" valueBlobFile="ORGANISATION/PICTURE/blobFiles/f16d9cd735b3e374cb33ff88136ad847"/>
      <column name="DATE_NEW" valueDate="2023-09-08T10:29:34"/>
    </insert>
    <insert tableName="ORGANISATION">
      <column name="ORGANISATIONID" value="82c7b72d-da4e-4fab-a6cc-31e1be07dd08"/>
      <column name="KIND" value="ORGPROSPECT"/>
      <column name="NAME" value="Pichelmaier Financial  AG"/>
      <column name="DATE_EDIT" valueDate="2023-03-22T12:59:58"/>
      <column name="CUSTOMERCODE" value="3579"/>
      <column name="USER_EDIT" value="Admin"/>
      <column name="USER_NEW" value="Admin"/>
      <column name="PICTURE" valueBlobFile="ORGANISATION/PICTURE/blobFiles/8f08401c40ecc2590a116f3dd6d95b3c"/>
      <column name="DATE_NEW" valueDate="2021-02-03T01:16:04"/>
    </insert>
    <insert tableName="ORGANISATION">
      <column name="ORGANISATIONID" value="8c7996ef-265a-4c6c-a7ec-9ad78eaaed0b"/>
      <column name="KIND" value="ORGSUP"/>
      <column name="NAME" value="Meister Messebau"/>
      <column name="DATE_EDIT" valueDate="2023-07-09T08:28:34"/>
      <column name="CUSTOMERCODE" value="0500"/>
      <column name="USER_EDIT" value="Lisa Sommer"/>
      <column name="USER_NEW" value="Admin"/>
      <column name="PICTURE" valueBlobFile="ORGANISATION/PICTURE/blobFiles/792b5ad89f72d2bc7af3e2725aa17ea2"/>
      <column name="DATE_NEW" valueDate="2023-03-22T09:32:22"/>
    </insert>
    <insert tableName="ORGANISATION">
      <column name="ORGANISATIONID" value="8f4f43e0-669b-4e1f-b050-42193f8d2998"/>
      <column name="KIND" value="ORGCUTOMER"/>
      <column name="NAME" value="Sevent SE"/>
      <column name="DATE_EDIT" valueDate="2023-03-22T01:00:38"/>
      <column name="CUSTOMERCODE" value="7878"/>
      <column name="USER_EDIT" value="Admin"/>
      <column name="USER_NEW" value="Admin"/>
      <column name="PICTURE" valueBlobFile="ORGANISATION/PICTURE/blobFiles/e78887cd6de6178da2e18870c6a837ab"/>
      <column name="INFO" value="Automobilvermietung"/>
      <column name="DATE_NEW" valueDate="2021-02-07T09:41:44"/>
    </insert>
    <insert tableName="ORGANISATION">
      <column name="ORGANISATIONID" value="9751667e-f42c-4007-a393-41c189fde022"/>
      <column name="NAME" value="MedMeier GmbH"/>
      <column name="DATE_EDIT" valueDate="2023-07-12T07:40:46"/>
      <column name="CUSTOMERCODE" value="6510"/>
      <column name="USER_EDIT" value="Admin"/>
      <column name="USER_NEW" value="Admin"/>
      <column name="DATE_NEW" valueDate="2023-07-10T09:05:14"/>
    </insert>
    <insert tableName="ORGANISATION">
      <column name="ORGANISATIONID" value="97b66b3c-a9f5-4dc4-902e-850d69973d1d"/>
      <column name="KIND" value="ORGPROSPECT"/>
      <column name="NAME" value="Bucher Unternehmensgruppe"/>
      <column name="DATE_EDIT" valueDate="2023-03-22T12:39:40"/>
      <column name="CUSTOMERCODE" value="3698"/>
      <column name="USER_EDIT" value="Admin"/>
      <column name="USER_NEW" value="Admin"/>
      <column name="PICTURE" valueBlobFile="ORGANISATION/PICTURE/blobFiles/d3ff7163fa5dc136d5717d61fa04c790"/>
      <column name="DATE_NEW" valueDate="2021-02-07T09:49:26"/>
    </insert>
    <insert tableName="ORGANISATION">
      <column name="ORGANISATIONID" value="993b5eb0-9cf6-40f4-9b82-e383cf3ebd67"/>
      <column name="KIND" value="ORGSUP"/>
      <column name="NAME" value="Meister Messebau GmbH"/>
      <column name="DATE_EDIT" valueDate="2023-07-09T08:28:44"/>
      <column name="CUSTOMERCODE" value="0500"/>
      <column name="USER_EDIT" value="Lisa Sommer"/>
      <column name="USER_NEW" value="Admin"/>
      <column name="PICTURE" valueBlobFile="ORGANISATION/PICTURE/blobFiles/792b5ad89f72d2bc7af3e2725aa17ea2"/>
      <column name="DATE_NEW" valueDate="2023-03-22T09:28:22"/>
    </insert>
    <insert tableName="ORGANISATION">
      <column name="ORGANISATIONID" value="9964b1b2-630d-4f4e-94cd-fa5f3368cc49"/>
      <column name="KIND" value="ORGSUP"/>
      <column name="NAME" value="Horn Schramm AG &amp; Co. OHG"/>
      <column name="DATE_EDIT" valueDate="2023-07-09T08:21:33"/>
      <column name="CUSTOMERCODE" value="0200"/>
      <column name="USER_EDIT" value="Lisa Sommer"/>
      <column name="USER_NEW" value="Lisa Sommer"/>
      <column name="DATE_NEW" valueDate="2023-07-09T09:22:28"/>
    </insert>
    <insert tableName="ORGANISATION">
      <column name="ORGANISATIONID" value="a0111431-e12c-4790-9dd2-167cb9b345ea"/>
      <column name="KIND" value="ORGCUTOMER"/>
      <column name="NAME" value="Emil Brandstätter AG"/>
      <column name="DATE_EDIT" valueDate="2023-09-08T11:01:08"/>
      <column name="CUSTOMERCODE" value="5609"/>
      <column name="USER_EDIT" value="Admin"/>
      <column name="USER_NEW" value="Admin"/>
      <column name="DATE_NEW" valueDate="2023-09-08T09:35:40"/>
    </insert>
    <insert tableName="ORGANISATION">
      <column name="ORGANISATIONID" value="a0e1c65c-13c7-4f6f-85df-ea860d743de5"/>
      <column name="NAME" value="Scherrer Gr"/>
      <column name="USER_NEW" value="Admin"/>
      <column name="DATE_NEW" valueDate="2023-07-11T11:53:53"/>
    </insert>
    <insert tableName="ORGANISATION">
      <column name="ORGANISATIONID" value="a331acfd-00fa-4ec8-a8b1-750362341bcc"/>
      <column name="KIND" value="ORGCUTOMER"/>
      <column name="NAME" value="Winter AG "/>
      <column name="DATE_EDIT" valueDate="2023-09-08T10:57:32"/>
      <column name="CUSTOMERCODE" value="0753"/>
      <column name="USER_EDIT" value="Admin"/>
      <column name="USER_NEW" value="Admin"/>
      <column name="DATE_NEW" valueDate="2023-09-08T09:42:15"/>
    </insert>
    <insert tableName="ORGANISATION">
      <column name="ORGANISATIONID" value="a5d107ac-f796-430e-a686-5a132f96650b"/>
      <column name="KIND" value="ORGCUTOMER"/>
      <column name="NAME" value="SuperBauer AG"/>
      <column name="DATE_EDIT" valueDate="2022-05-17T09:23:29"/>
      <column name="CUSTOMERCODE" value="3232"/>
      <column name="USER_EDIT" value="Admin"/>
      <column name="USER_NEW" value="Admin"/>
      <column name="PICTURE" valueBlobFile="ORGANISATION/PICTURE/blobFiles/f968316347309bfa3bafc5db871b46fc"/>
      <column name="INFO" value="ab Mitte 2024 interessant"/>
      <column name="DATE_NEW" valueDate="2021-02-07T09:46:03"/>
    </insert>
    <insert tableName="ORGANISATION">
      <column name="ORGANISATIONID" value="ae5f2195-fa5c-4961-9f31-1d21984b4bec"/>
      <column name="KIND" value="ORGCUTOMER"/>
      <column name="NAME" value="Korner GmbH"/>
      <column name="DATE_EDIT" valueDate="2023-09-08T12:14:12"/>
      <column name="CUSTOMERCODE" value="5614"/>
      <column name="USER_EDIT" value="Admin"/>
      <column name="USER_NEW" value="Admin"/>
      <column name="DATE_NEW" valueDate="2023-09-08T09:54:21"/>
    </insert>
    <insert tableName="ORGANISATION">
      <column name="ORGANISATIONID" value="aed65442-06aa-4cdc-b924-1d9728b444d3"/>
      <column name="KIND" value="ORGPARTNER"/>
      <column name="NAME" value="Schild AG"/>
      <column name="DATE_EDIT" valueDate="2023-03-22T01:00:20"/>
      <column name="CUSTOMERCODE" value="6758"/>
      <column name="USER_EDIT" value="Admin"/>
      <column name="USER_NEW" value="Admin"/>
      <column name="PICTURE" valueBlobFile="ORGANISATION/PICTURE/blobFiles/9e971b8933606dce110ebebeef86683c"/>
      <column name="DATE_NEW" valueDate="2021-02-13T10:53:45"/>
    </insert>
    <insert tableName="ORGANISATION">
      <column name="ORGANISATIONID" value="b043cd42-058c-48bd-8326-4c92e0e74c48"/>
      <column name="KIND" value="ORGPROSPECT"/>
      <column name="NAME" value="Waken Neuser SE"/>
      <column name="DATE_EDIT" valueDate="2023-03-22T01:01:47"/>
      <column name="CUSTOMERCODE" value="5612"/>
      <column name="USER_EDIT" value="Admin"/>
      <column name="USER_NEW" value="Admin"/>
      <column name="PICTURE" valueBlobFile="ORGANISATION/PICTURE/blobFiles/0ce79f41c14a4f1eaddf0699a78cf7e4"/>
      <column name="DATE_NEW" valueDate="2021-02-07T09:43:55"/>
    </insert>
    <insert tableName="ORGANISATION">
      <column name="ORGANISATIONID" value="b6f2392a-a4b9-4783-b060-317b4b6a28e8"/>
      <column name="KIND" value="ORGSUP"/>
      <column name="NAME" value="Scherrer Group"/>
      <column name="DATE_EDIT" valueDate="2023-07-09T08:21:55"/>
      <column name="CUSTOMERCODE" value="0400"/>
      <column name="USER_EDIT" value="Lisa Sommer"/>
      <column name="USER_NEW" value="Lisa Sommer"/>
      <column name="DATE_NEW" valueDate="2023-07-09T09:18:39"/>
    </insert>
    <insert tableName="ORGANISATION">
      <column name="ORGANISATIONID" value="bc81b848-5574-4245-bfe8-61ffaf8b8761"/>
      <column name="NAME" value="Trio Bau GmbH"/>
      <column name="USER_NEW" value="Admin"/>
      <column name="DATE_NEW" valueDate="2023-07-11T11:47:02"/>
    </insert>
    <insert tableName="ORGANISATION">
      <column name="ORGANISATIONID" value="bd92680c-fb4b-4f9b-b434-da4fcee5b079"/>
      <column name="KIND" value="ORGMANUF"/>
      <column name="NAME" value="Netro AG"/>
      <column name="DATE_EDIT" valueDate="2023-03-22T12:58:47"/>
      <column name="CUSTOMERCODE" value="6354"/>
      <column name="USER_EDIT" value="Admin"/>
      <column name="USER_NEW" value="Admin"/>
      <column name="PICTURE" valueBlobFile="ORGANISATION/PICTURE/blobFiles/c051e322daa940ba12cb98c56fafbf8f"/>
      <column name="DATE_NEW" valueDate="2021-02-13T08:38:18"/>
    </insert>
    <insert tableName="ORGANISATION">
      <column name="ORGANISATIONID" value="c0f7723e-5d7b-42f2-b5fd-78c9d509a62f"/>
      <column name="KIND" value="ORGCUTOMER"/>
      <column name="NAME" value="Fischer AG"/>
      <column name="DATE_EDIT" valueDate="2023-03-23T08:22:13"/>
      <column name="CUSTOMERCODE" value="1018"/>
      <column name="USER_EDIT" value="Admin"/>
      <column name="USER_NEW" value="Birgit Leicht"/>
      <column name="DATE_NEW" valueDate="2023-03-22T03:43:20"/>
    </insert>
    <insert tableName="ORGANISATION">
      <column name="ORGANISATIONID" value="c1739d71-3815-4cc5-8aea-0800624c896a"/>
      <column name="KIND" value="ORGCUTOMER"/>
      <column name="NAME" value="Tech Tools GmbH"/>
      <column name="DATE_EDIT" valueDate="2023-07-11T10:49:11"/>
      <column name="CUSTOMERCODE" value="2890"/>
      <column name="USER_EDIT" value="Admin"/>
      <column name="USER_NEW" value="Admin"/>
      <column name="DATE_NEW" valueDate="2023-09-08T09:42:52"/>
    </insert>
    <insert tableName="ORGANISATION">
      <column name="ORGANISATIONID" value="c8093b3c-0100-4746-9f37-e42a5861ce68"/>
      <column name="KIND" value="ORGPROSPECT"/>
      <column name="NAME" value="Pluto GmbH"/>
      <column name="DATE_EDIT" valueDate="2023-09-08T10:58:51"/>
      <column name="CUSTOMERCODE" value="7110"/>
      <column name="USER_EDIT" value="Admin"/>
      <column name="USER_NEW" value="Admin"/>
      <column name="DATE_NEW" valueDate="2023-09-08T09:33:54"/>
    </insert>
    <insert tableName="ORGANISATION">
      <column name="ORGANISATIONID" value="cadc12d1-999e-4874-aaa5-0a4bba60ae36"/>
      <column name="KIND" value="ORGCUTOMER"/>
      <column name="NAME" value="Sommer AG "/>
      <column name="DATE_EDIT" valueDate="2023-09-08T09:51:40"/>
      <column name="CUSTOMERCODE" value="0987"/>
      <column name="USER_EDIT" value="Admin"/>
      <column name="USER_NEW" value="Admin"/>
      <column name="DATE_NEW" valueDate="2023-09-08T09:31:59"/>
    </insert>
    <insert tableName="ORGANISATION">
      <column name="ORGANISATIONID" value="ce78fb04-13c9-4feb-8902-a7d6e2313a54"/>
      <column name="KIND" value="ORGCUTOMER"/>
      <column name="NAME" value="Fahey, Spencer and Armstrong"/>
      <column name="DATE_EDIT" valueDate="2023-03-23T08:10:19"/>
      <column name="CUSTOMERCODE" value="1793"/>
      <column name="USER_EDIT" value="Admin"/>
      <column name="USER_NEW" value="Birgit Leicht"/>
      <column name="DATE_NEW" valueDate="2023-03-22T03:00:03"/>
    </insert>
    <insert tableName="ORGANISATION">
      <column name="ORGANISATIONID" value="d1538762-23f3-4e4d-9e0b-948c01bb5a8d"/>
      <column name="KIND" value="ORGCUTOMER"/>
      <column name="NAME" value="Rixer OHG"/>
      <column name="DATE_EDIT" valueDate="2023-09-08T12:14:31"/>
      <column name="CUSTOMERCODE" value="5009"/>
      <column name="USER_EDIT" value="Admin"/>
      <column name="USER_NEW" value="Admin"/>
      <column name="DATE_NEW" valueDate="2023-09-08T09:41:36"/>
    </insert>
    <insert tableName="ORGANISATION">
      <column name="ORGANISATIONID" value="d3707591-5620-49a8-a63f-19e88ca7a21c"/>
      <column name="KIND" value="ORGPROSPECT"/>
      <column name="NAME" value="MNF Versicherung"/>
      <column name="DATE_EDIT" valueDate="2023-03-22T12:51:12"/>
      <column name="CUSTOMERCODE" value="7691"/>
      <column name="USER_EDIT" value="Admin"/>
      <column name="USER_NEW" value="Admin"/>
      <column name="PICTURE" valueBlobFile="ORGANISATION/PICTURE/blobFiles/5f8761049904f992654d5d2eda8c4299"/>
      <column name="DATE_NEW" valueDate="2021-02-03T01:16:04"/>
    </insert>
    <insert tableName="ORGANISATION">
      <column name="ORGANISATIONID" value="d9c14abe-bd50-466e-86a3-40aa31e90012"/>
      <column name="KIND" value="ORGPROSPECT"/>
      <column name="NAME" value="Nedick's"/>
      <column name="DATE_EDIT" valueDate="2023-07-09T08:24:30"/>
      <column name="CUSTOMERCODE" value="8326"/>
      <column name="USER_EDIT" value="Lisa Sommer"/>
      <column name="USER_NEW" value="Admin"/>
      <column name="DATE_NEW" valueDate="2023-07-11T07:08:15"/>
    </insert>
    <insert tableName="ORGANISATION">
      <column name="ORGANISATIONID" value="e522947d-bd2d-4b11-a53b-a136aca28b8e"/>
      <column name="KIND" value="ORGPROSPECT"/>
      <column name="NAME" value="Ertl GmbH"/>
      <column name="DATE_EDIT" valueDate="2023-07-11T10:49:54"/>
      <column name="CUSTOMERCODE" value="7824"/>
      <column name="USER_EDIT" value="Admin"/>
      <column name="USER_NEW" value="Admin"/>
      <column name="DATE_NEW" valueDate="2023-09-08T09:56:28"/>
    </insert>
    <insert tableName="ORGANISATION">
      <column name="ORGANISATIONID" value="e7b49a57-8789-47a2-8762-377cf28f8be2"/>
      <column name="KIND" value="ORGCUTOMER"/>
      <column name="NAME" value="Rumpel GmbH"/>
      <column name="DATE_EDIT" valueDate="2023-09-08T12:15:52"/>
      <column name="CUSTOMERCODE" value="6542"/>
      <column name="USER_EDIT" value="Admin"/>
      <column name="USER_NEW" value="Admin"/>
      <column name="DATE_NEW" valueDate="2023-09-08T09:44:48"/>
    </insert>
    <insert tableName="ORGANISATION">
      <column name="ORGANISATIONID" value="e9ac1e92-06dc-41f8-aa81-f3b57b299f0d"/>
      <column name="KIND" value="ORGCUTOMER"/>
      <column name="NAME" value="Bornheimer Maschinenfabrik GmbH"/>
      <column name="CUSTOMERCODE" value="4387"/>
      <column name="USER_NEW" value="Admin"/>
      <column name="DATE_NEW" valueDate="2023-09-08T09:33:40"/>
    </insert>
    <insert tableName="ORGANISATION">
      <column name="ORGANISATIONID" value="ea07af40-4918-4ea2-94ad-031d01aeaab4"/>
      <column name="KIND" value="ORGPROSPECT"/>
      <column name="NAME" value="International Kältetechnik AG"/>
      <column name="DATE_EDIT" valueDate="2023-03-22T12:40:37"/>
      <column name="CUSTOMERCODE" value="6983"/>
      <column name="USER_EDIT" value="Admin"/>
      <column name="USER_NEW" value="Admin"/>
      <column name="PICTURE" valueBlobFile="ORGANISATION/PICTURE/blobFiles/f0524cce27226fe86266fba15280d1a0"/>
      <column name="DATE_NEW" valueDate="2021-02-03T01:16:04"/>
    </insert>
    <insert tableName="ORGANISATION">
      <column name="ORGANISATIONID" value="f2d429b5-78cb-4069-8af5-90d53ad0c4e6"/>
      <column name="KIND" value="ORGPROSPECT"/>
      <column name="NAME" value="OmniTech"/>
      <column name="DATE_EDIT" valueDate="2023-07-09T08:24:44"/>
      <column name="CUSTOMERCODE" value="1379"/>
      <column name="USER_EDIT" value="Lisa Sommer"/>
      <column name="USER_NEW" value="Admin"/>
      <column name="DATE_NEW" valueDate="2023-07-09T09:01:10"/>
    </insert>
    <insert tableName="ORGANISATION">
      <column name="ORGANISATIONID" value="f687f722-8b4e-4acc-afa2-2a1ae1d17d67"/>
      <column name="NAME" value="TRI bau"/>
      <column name="USER_NEW" value="Admin"/>
      <column name="DATE_NEW" valueDate="2023-07-11T11:49:54"/>
    </insert>
    <insert tableName="ORGANISATION">
      <column name="ORGANISATIONID" value="f7b8f0c3-7702-4466-b502-d21fa4fa0010"/>
      <column name="KIND" value="ORGCUTOMER"/>
      <column name="NAME" value="Skyscraper Bau GmbH"/>
      <column name="DATE_EDIT" valueDate="2023-03-22T01:00:56"/>
      <column name="CUSTOMERCODE" value="1236"/>
      <column name="USER_EDIT" value="Admin"/>
      <column name="USER_NEW" value="Admin"/>
      <column name="PICTURE" valueBlobFile="ORGANISATION/PICTURE/blobFiles/be597b2abd1799f6b9cc981b2ba04244"/>
      <column name="INFO" value="Die Skyscraper Bau GmbH zählt zu den führenden Unternehmen in der Baubranche. Mit ihrem breiten Portfolio überzeugen sie regelmäßig und diversifizieren sich von ihren Mitbewerbern. "/>
      <column name="DATE_NEW" valueDate="2021-02-05T03:33:25"/>
    </insert>
    <insert tableName="ORGANISATION">
      <column name="ORGANISATIONID" value="fa10b60f-9afc-4e79-91d4-63ae0b636ac7"/>
      <column name="KIND" value="ORGSUP"/>
      <column name="NAME" value="Marty AG"/>
      <column name="DATE_EDIT" valueDate="2023-07-09T08:21:42"/>
      <column name="CUSTOMERCODE" value="0300"/>
      <column name="USER_EDIT" value="Lisa Sommer"/>
      <column name="USER_NEW" value="Lisa Sommer"/>
      <column name="DATE_NEW" valueDate="2023-07-09T09:13:47"/>
    </insert>
    <insert tableName="ORGANISATION">
      <column name="ORGANISATIONID" value="fc583d56-bd9a-4f3c-bdb9-0b7d4b1ecf92"/>
      <column name="KIND" value="ORGSUP"/>
      <column name="NAME" value="Hamel Collin SAS"/>
      <column name="DATE_EDIT" valueDate="2023-07-09T08:21:14"/>
      <column name="CUSTOMERCODE" value="0100"/>
      <column name="USER_EDIT" value="Lisa Sommer"/>
      <column name="USER_NEW" value="Lisa Sommer"/>
      <column name="DATE_NEW" valueDate="2023-07-09T09:25:38"/>
    </insert>
    <insert tableName="ORGANISATION">
      <column name="ORGANISATIONID" value="fd58545c-cb5a-42f0-9cae-3dc767cfaf76"/>
      <column name="KIND" value="ORGPROSPECT"/>
      <column name="NAME" value="Parker &amp; Jenkins"/>
      <column name="DATE_EDIT" valueDate="2023-07-02T09:43:51"/>
      <column name="CUSTOMERCODE" value="1431"/>
      <column name="USER_EDIT" value="Birgit Leicht"/>
      <column name="USER_NEW" value="Admin"/>
      <column name="DATE_NEW" valueDate="2023-03-24T07:30:41"/>
    </insert>
  </changeSet>
</databaseChangeLog>